{
    "sm_recover_hp":{
        "title":"Recover Hp",
        "target_type":"none",
        "class":"sk_auto_recovery",
        "max_lv":10,
        "heal_val":[5,10,15,20,25,30,35,40,45,50]
    },
    "sm_stun":{
        "title":"Stun",
        "target_type":"enemy",
        "class":"sk_stun",
        "max_lv":5,
        "sp_cost":10,
        "atk_mul":2,
        "cast_time":2000,
        "delay":1000,
        "range":5,
        "cooldown":500,
        "chance":[0.2, 0.4, 0.6, 0.8, 0.9],
        "stun_time":[1, 1, 2, 2, 3]
    }
}